planqk/api/__init__.py
planqk/api/_version.py
planqk/api/client.py
planqk/api/credentials.py
planqk/api/sdk/__init__.py
planqk/api/sdk/client.py
planqk/api/sdk/environment.py
planqk/api/sdk/core/__init__.py
planqk/api/sdk/core/api_error.py
planqk/api/sdk/core/client_wrapper.py
planqk/api/sdk/core/datetime_utils.py
planqk/api/sdk/core/file.py
planqk/api/sdk/core/force_multipart.py
planqk/api/sdk/core/http_client.py
planqk/api/sdk/core/http_response.py
planqk/api/sdk/core/jsonable_encoder.py
planqk/api/sdk/core/pydantic_utilities.py
planqk/api/sdk/core/query_encoder.py
planqk/api/sdk/core/remove_none_from_dict.py
planqk/api/sdk/core/request_options.py
planqk/api/sdk/core/serialization.py
planqk/api/sdk/data_pools/__init__.py
planqk/api/sdk/data_pools/client.py
planqk/api/sdk/data_pools/raw_client.py
planqk/api/sdk/errors/__init__.py
planqk/api/sdk/errors/bad_request_error.py
planqk/api/sdk/errors/forbidden_error.py
planqk/api/sdk/errors/internal_server_error.py
planqk/api/sdk/errors/not_found_error.py
planqk/api/sdk/errors/unauthorized_error.py
planqk/api/sdk/types/__init__.py
planqk/api/sdk/types/data_pool_dto.py
planqk/api/sdk/types/data_pool_dto_current_user_permission.py
planqk/api/sdk/types/data_pool_file_dto.py
planqk/api/sdk/types/oauth_scope.py
planqk_api_sdk-1.9.3.dist-info/licenses/LICENSE
planqk_api_sdk-1.9.3.dist-info/METADATA
planqk_api_sdk-1.9.3.dist-info/WHEEL
planqk_api_sdk-1.9.3.dist-info/top_level.txt
planqk_api_sdk-1.9.3.dist-info/RECORD
