Metadata-Version: 2.4
Name: planqk-api-sdk
Version: 1.9.3
Summary: SDK to interact with the official PLANQK API.
Author-email: Kipu Quantum GmbH <info@kipu-quantum.com>
Maintainer-email: Michael Wurster <michael.wurster@kipu-quantum.com>, Lukas Harzenetter <lukas.harzenetter@kipu-quantum.com>
License:                                  Apache License
Project-URL: Homepage, https://hub.kipu-quantum.com
Project-URL: Documentation, https://docs.hub.kipu-quantum.com
Project-URL: Repository, https://gitlab.com/planqk-foss/planqk-api-sdk
Project-URL: Issues, https://gitlab.com/planqk-foss/planqk-api-sdk/-/issues
Project-URL: Changelog, https://gitlab.com/planqk-foss/planqk-api-sdk/-/releases
Classifier: Programming Language :: Python :: 3
Classifier: License :: OSI Approved :: Apache Software License
Classifier: Operating System :: OS Independent
Requires-Python: >=3.9
License-File: LICENSE
Requires-Dist: authlib>=1.5.1
Requires-Dist: deprecated>=1.2.18
Requires-Dist: httpx>=0.28.1
Requires-Dist: pydantic<2.10,>=2.5.0
Dynamic: license-file
